batopt/__init__(Conflicted copy 2021-03-19 by DESKTOP-VRE38DV).py
batopt/__init__.py
batopt/_nbdev(Conflicted copy 2021-03-19 by DESKTOP-VRE38DV).py
batopt/_nbdev.py
batopt/charge(Conflicted copy 2021-03-19 by DESKTOP-VRE38DV).py
batopt/charge.py
batopt/christmas(Conflicted copy 2021-03-19 by DESKTOP-VRE38DV).py
batopt/christmas.py
batopt/clean(Conflicted copy 2021-03-19 by DESKTOP-VRE38DV).py
batopt/clean.py
batopt/constraints(Conflicted copy 2021-03-19 by DESKTOP-VRE38DV).py
batopt/constraints.py
batopt/discharge(Conflicted copy 2021-03-19 by DESKTOP-VRE38DV).py
batopt/discharge.py
batopt/eval.py
batopt/pipeline(Conflicted copy 2021-03-19 by DESKTOP-VRE38DV).py
batopt/pipeline.py
batopt/pv(Conflicted copy 2021-03-19 by DESKTOP-VRE38DV).py
batopt/pv.py
batopt/retrieval(Conflicted copy 2021-03-19 by DESKTOP-VRE38DV).py
batopt/retrieval.py
batopt/similar.py
batopt/tuning(Conflicted copy 2021-03-19 by DESKTOP-VRE38DV).py
batopt/tuning.py
batopt/utils(Conflicted copy 2021-03-19 by DESKTOP-VRE38DV).py
batopt/utils.py
batopt-0.0.4.dist-info/METADATA
batopt-0.0.4.dist-info/WHEEL
batopt-0.0.4.dist-info/top_level.txt
batopt-0.0.4.dist-info/RECORD
