Metadata-Version: 2.1
Name: batopt
Version: 0.0.4
Summary: This module allows the user to reproduce the workflow used by the UCL ESAIL team for submissions to the Western Power Distribition Data Science competition
Home-page: https://github.com/AyrtonB/WPD-DS-Challenge
Author: Ayrton Bourn, Patrick De Mars
Author-email: ayrton.bourn.18@ucl.ac.uk
License: UNKNOWN
Platform: UNKNOWN
Classifier: Programming Language :: Python :: 3
Requires-Python: >=3.6
